{"list": [{"id": "2146958", "icon": "http://image.digitalarchives.tw/Thumbnail/00/5b/45/f9.jpg", "title": "中文種名:青脆枝", "url": "00/20/c2/8e.html", "publisher": "中央研究院 生物多樣性研究中心 植物標本館 Herbarium, Research Center for Biodiversity, Academia Sinica, Taipei (HAST)"}, {"id": "2146961", "icon": "http://image.digitalarchives.tw/Thumbnail/00/5b/46/04.jpg", "title": "中文種名:青脆枝", "url": "00/20/c2/91.html", "publisher": "中央研究院 生物多樣性研究中心 植物標本館 Herbarium, Research Center for Biodiversity, Academia Sinica, Taipei (HAST)"}, {"id": "2146983", "icon": "http://image.digitalarchives.tw/Thumbnail/00/5b/46/65.jpg", "title": "中文種名:呂宋毛蕊木", "url": "00/20/c2/a7.html", "publisher": "中央研究院 生物多樣性研究中心 植物標本館 Herbarium, Research Center for Biodiversity, Academia Sinica, Taipei (HAST)"}, {"id": "2147133", "icon": "http://image.digitalarchives.tw/Thumbnail/00/5a/10/6c.jpg", "title": "中文種名:白花八角", "url": "00/20/c3/3d.html", "publisher": "中央研究院 生物多樣性研究中心 植物標本館 Herbarium, Research Center for Biodiversity, Academia Sinica, Taipei (HAST)"}, {"id": "2147262", "icon": "http://image.digitalarchives.tw/Thumbnail/00/5a/13/2a.jpg", "title": "中文種名:台灣八角", "url": "00/20/c3/be.html", "publisher": "中央研究院 生物多樣性研究中心 植物標本館 Herbarium, Research Center for Biodiversity, Academia Sinica, Taipei (HAST)"}, {"id": "2147315", "icon": "http://image.digitalarchives.tw/Thumbnail/00/5a/14/41.jpg", "title": "中文種名:台灣八角", "url": "00/20/c3/f3.html", "publisher": "中央研究院 生物多樣性研究中心 植物標本館 Herbarium, Research Center for Biodiversity, Academia Sinica, Taipei (HAST)"}, {"id": "2147794", "icon": "http://image.digitalarchives.tw/Thumbnail/00/59/9a/bf.jpg", "title": "中文種名:白花八角", "url": "00/20/c5/d2.html", "publisher": "中央研究院 生物多樣性研究中心 植物標本館 Herbarium, Research Center for Biodiversity, Academia Sinica, Taipei (HAST)"}, {"id": "2147793", "icon": "http://image.digitalarchives.tw/Thumbnail/00/59/9a/be.jpg", "title": "中文種名:台灣八角", "url": "00/20/c5/d1.html", "publisher": "中央研究院 生物多樣性研究中心 植物標本館 Herbarium, Research Center for Biodiversity, Academia Sinica, Taipei (HAST)"}, {"id": "2148259", "icon": "http://image.digitalarchives.tw/Thumbnail/00/5b/4d/52.jpg", "title": "中文種名:白花八角", "url": "00/20/c7/a3.html", "publisher": "中央研究院 生物多樣性研究中心 植物標本館 Herbarium, Research Center for Biodiversity, Academia Sinica, Taipei (HAST)"}, {"id": "2148291", "icon": "http://image.digitalarchives.tw/Thumbnail/00/5b/4d/98.jpg", "title": "中文種名:青脆枝", "url": "00/20/c7/c3.html", "publisher": "中央研究院 生物多樣性研究中心 植物標本館 Herbarium, Research Center for Biodiversity, Academia Sinica, Taipei (HAST)"}, {"id": "2148343", "icon": "http://image.digitalarchives.tw/Thumbnail/00/5b/4e/21.jpg", "title": "中文種名:阿里山五味子", "url": "00/20/c7/f7.html", "publisher": "中央研究院 生物多樣性研究中心 植物標本館 Herbarium, Research Center for Biodiversity, Academia Sinica, Taipei (HAST)"}, {"id": "2148521", "icon": "http://image.digitalarchives.tw/Thumbnail/00/5b/50/45.jpg", "title": "中文種名:台灣八角", "url": "00/20/c8/a9.html", "publisher": "中央研究院 生物多樣性研究中心 植物標本館 Herbarium, Research Center for Biodiversity, Academia Sinica, Taipei (HAST)"}, {"id": "2148556", "icon": "http://image.digitalarchives.tw/Thumbnail/00/5b/50/b7.jpg", "title": "中文種名:台灣八角", "url": "00/20/c8/cc.html", "publisher": "中央研究院 生物多樣性研究中心 植物標本館 Herbarium, Research Center for Biodiversity, Academia Sinica, Taipei (HAST)"}, {"id": "2148566", "icon": "http://image.digitalarchives.tw/Thumbnail/00/5b/50/cd.jpg", "title": "中文種名:白花八角", "url": "00/20/c8/d6.html", "publisher": "中央研究院 生物多樣性研究中心 植物標本館 Herbarium, Research Center for Biodiversity, Academia Sinica, Taipei (HAST)"}, {"id": "2149037", "icon": "http://image.digitalarchives.tw/Thumbnail/00/5b/58/93.jpg", "title": "中文種名:白花八角", "url": "00/20/ca/ad.html", "publisher": "中央研究院 生物多樣性研究中心 植物標本館 Herbarium, Research Center for Biodiversity, Academia Sinica, Taipei (HAST)"}, {"id": "2149151", "icon": "http://image.digitalarchives.tw/Thumbnail/00/5b/5a/33.jpg", "title": "中文種名:柿葉茶茱萸", "url": "00/20/cb/1f.html", "publisher": "中央研究院 生物多樣性研究中心 植物標本館 Herbarium, Research Center for Biodiversity, Academia Sinica, Taipei (HAST)"}, {"id": "2149288", "icon": "http://image.digitalarchives.tw/Thumbnail/00/5b/5e/af.jpg", "title": "中文種名:白花八角", "url": "00/20/cb/a8.html", "publisher": "中央研究院 生物多樣性研究中心 植物標本館 Herbarium, Research Center for Biodiversity, Academia Sinica, Taipei (HAST)"}, {"id": "2149313", "icon": "http://image.digitalarchives.tw/Thumbnail/00/5b/5f/06.jpg", "title": "中文種名:青脆枝", "url": "00/20/cb/c1.html", "publisher": "中央研究院 生物多樣性研究中心 植物標本館 Herbarium, Research Center for Biodiversity, Academia Sinica, Taipei (HAST)"}, {"id": "2149333", "icon": "http://image.digitalarchives.tw/Thumbnail/00/5b/5f/46.jpg", "title": "中文種名:台灣八角", "url": "00/20/cb/d5.html", "publisher": "中央研究院 生物多樣性研究中心 植物標本館 Herbarium, Research Center for Biodiversity, Academia Sinica, Taipei (HAST)"}, {"id": "2149369", "icon": "http://image.digitalarchives.tw/Thumbnail/00/5b/60/51.jpg", "title": "中文種名:台灣八角", "url": "00/20/cb/f9.html", "publisher": "中央研究院 生物多樣性研究中心 植物標本館 Herbarium, Research Center for Biodiversity, Academia Sinica, Taipei (HAST)"}, {"id": "2149423", "icon": "http://image.digitalarchives.tw/Thumbnail/00/5b/62/51.jpg", "title": "中文種名:青脆枝", "url": "00/20/cc/2f.html", "publisher": "中央研究院 生物多樣性研究中心 植物標本館 Herbarium, Research Center for Biodiversity, Academia Sinica, Taipei (HAST)"}, {"id": "2149485", "icon": "http://image.digitalarchives.tw/Thumbnail/00/5b/63/71.jpg", "title": "中文種名:台灣八角", "url": "00/20/cc/6d.html", "publisher": "中央研究院 生物多樣性研究中心 植物標本館 Herbarium, Research Center for Biodiversity, Academia Sinica, Taipei (HAST)"}, {"id": "2149686", "icon": "http://image.digitalarchives.tw/Thumbnail/00/5b/68/09.jpg", "title": "中文種名:台灣八角", "url": "00/20/cd/36.html", "publisher": "中央研究院 生物多樣性研究中心 植物標本館 Herbarium, Research Center for Biodiversity, Academia Sinica, Taipei (HAST)"}, {"id": "2149804", "icon": "http://image.digitalarchives.tw/Thumbnail/00/5b/6a/3e.jpg", "title": "中文種名:台灣八角", "url": "00/20/cd/ac.html", "publisher": "中央研究院 生物多樣性研究中心 植物標本館 Herbarium, Research Center for Biodiversity, Academia Sinica, Taipei (HAST)"}], "count": 118162, "nowpage": 3, "pagesize": 24}